html_parsing/__init__.py
html_parsing/feild_extraction.py
html_parsing/field_extraction.py
html_parsing/utils.py
rm_duplicates/__init__.py
rm_duplicates/simhash.py
rm_duplicates/utils.py
tests/__init__.py
tests/test_.py
html_parsing_dqa-0.1.6.dist-info/METADATA
html_parsing_dqa-0.1.6.dist-info/WHEEL
html_parsing_dqa-0.1.6.dist-info/top_level.txt
html_parsing_dqa-0.1.6.dist-info/zip-safe
html_parsing_dqa-0.1.6.dist-info/RECORD
