Metadata-Version: 2.4
Name: html_parsing_dqa
Version: 0.1.6
Summary: utils for html parsing
Author: jinqiu
Author-email: jinqiu@xiaohongshu.com
Requires-Dist: bs4
Requires-Dist: tika
Requires-Dist: datetime
Requires-Dist: python-dateutil
Requires-Dist: jieba
Requires-Dist: simhash
Dynamic: author
Dynamic: author-email
Dynamic: requires-dist
Dynamic: summary
